inbox/__init__.py
inbox/admin.py
inbox/apps.py
inbox/google_utils.py
inbox/models.py
inbox/signals.py
inbox/utils.py
inbox/locale/ru_RU/LC_MESSAGES/django.mo
inbox/locale/ru_RU/LC_MESSAGES/django.po
inbox/management/__init__.py
inbox/management/commands/__init__.py
inbox/management/commands/getmail.py
inbox/management/commands/processincomingmessage.py
inbox/management/commands/rebuildmessageattachments.py
inbox/migrations/0001_initial.py
inbox/migrations/__init__.py
inbox/south_migrations/0001_initial.py
inbox/south_migrations/0002_auto__chg_field_mailbox_uri.py
inbox/south_migrations/0003_auto__add_field_mailbox_active.py
inbox/south_migrations/0004_auto__add_field_message_outgoing.py
inbox/south_migrations/0005_rename_fields.py
inbox/south_migrations/0006_auto__add_field_message_in_reply_to.py
inbox/south_migrations/0007_auto__del_field_message_address__add_field_message_from_header__add_fi.py
inbox/south_migrations/0008_populate_from_to_fields.py
inbox/south_migrations/0009_remove_references_table.py
inbox/south_migrations/0010_auto__add_field_mailbox_from_email.py
inbox/south_migrations/0011_auto__add_field_message_read.py
inbox/south_migrations/0012_auto__add_messageattachment.py
inbox/south_migrations/0013_auto__add_field_messageattachment_message.py
inbox/south_migrations/0014_migrate_message_attachments.py
inbox/south_migrations/0015_auto__add_field_messageattachment_headers.py
inbox/south_migrations/0016_auto__add_field_message_encoded.py
inbox/south_migrations/0017_auto__add_field_message_eml.py
inbox/south_migrations/__init__.py
inbox/tests/__init__.py
inbox/tests/base.py
inbox/tests/settings.py
inbox/tests/test_integration_imap.py
inbox/tests/test_mailbox.py
inbox/tests/test_message_flattening.py
inbox/tests/test_process_email.py
inbox/tests/test_processincomingmessage.py
inbox/tests/test_transports.py
inbox/transports/__init__.py
inbox/transports/babyl.py
inbox/transports/base.py
inbox/transports/generic.py
inbox/transports/gmail.py
django_mailbox_fork-42.0.1.dist-info/LICENSE
django_mailbox_fork-42.0.1.dist-info/METADATA
django_mailbox_fork-42.0.1.dist-info/WHEEL
django_mailbox_fork-42.0.1.dist-info/top_level.txt
django_mailbox_fork-42.0.1.dist-info/RECORD
